world_serpent/__init__.py
world_serpent/aggregation/__init__.py
world_serpent/aggregation/aggregation.py
world_serpent/aggregation/stage.py
world_serpent/utils/__init__.py
world_serpent/utils/typecheck.py
world_serpent-0.0.1.dist-info/LICENSE
world_serpent-0.0.1.dist-info/METADATA
world_serpent-0.0.1.dist-info/WHEEL
world_serpent-0.0.1.dist-info/top_level.txt
world_serpent-0.0.1.dist-info/RECORD
