Metadata-Version: 2.1
Name: world-serpent
Version: 0.0.1
Summary: Abstractions to assist the construction of Mongo Aggregations.
Home-page: https://github.com/johndavidmartinez/world-serpent
Author: John Martinez
License: UNKNOWN
Platform: UNKNOWN
